{
 "actions": [],
 "allow_rename": 1,
 "creation": "2024-04-20 09:18:28.432717",
 "doctype": "DocType",
 "editable_grid": 1,
 "engine": "InnoDB",
 "field_order": [
  "employee",
  "auditee_team_leader"
 ],
 "fields": [
  {
   "fieldname": "employee",
   "fieldtype": "Link",
   "in_list_view": 1,
   "label": "Employee",
   "options": "Company Employee",
   "reqd": 1
  },
  {
   "default": "0",
   "fieldname": "auditee_team_leader",
   "fieldtype": "Check",
   "in_list_view": 1,
   "label": "HOD"
  }
 ],
 "index_web_pages_for_search": 1,
 "istable": 1,
 "links": [],
 "modified": "2024-04-29 10:17:04.906115",
 "modified_by": "Administrator",
 "module": "Internal Audit Planner",
 "name": "Actual Auditees",
 "owner": "Administrator",
 "permissions": [],
 "sort_field": "creation",
 "sort_order": "DESC",
 "states": []
}